{
  "employee": [
    {
      "employeeID": "E_0007",
      "firstName": "Marilyn",
      "lastName": "Wright",
      "department": {
        "departmentCode": "LAWS",
        "departmentName": "Law and Society Program"
      },
      "position": "Auditing clerk",
      "computer": {
        "model": "Lenovo",
        "os": "Windows 10 Home"
      }
    },
    {
      "employeeID": "E_0006",
      "firstName": "Hector",
      "lastName": "J. Davis",
      "department": {
        "departmentCode": "IPLA",
        "departmentName": "ETS Project Management"
      },
      "position": "Traffic clerk",
      "computer": {
        "model": "MacBook",
        "os": "OS X"
      }
    },
    {
      "employeeID": "E_0008",
      "firstName": "Masato",
      "lastName": "Ishikuno",
      "department": {
        "departmentCode": "RESD",
        "departmentName": "Office of Research"
      },
      "position": "Digital image processor",
      "computer": {
        "model": "Sony",
        "os": "Windows 10 Ult"
      }
    }
  ]
}